request_decorator_handlers/__init__.py
request_decorator_handlers/core/__init__.py
request_decorator_handlers/core/actions.py
request_decorator_handlers/core/models.py
request_decorator_handlers/decorators/__init__.py
request_decorator_handlers/decorators/debug.py
request_decorator_handlers/logging/__init__.py
request_decorator_handlers/logging/formatter.py
request_decorator_handlers/logging/request_logger.py
request_decorator_handlers/parsing/__init__.py
request_decorator_handlers/parsing/html.py
request_decorator_handlers/parsing/json_path.py
request_decorator_handlers/validation/__init__.py
request_decorator_handlers/validation/json_validator.py
request_decorator_handlers/validation/response.py
request_decorator_handlers-0.1.6.dist-info/licenses/LICENSE
request_decorator_handlers-0.1.6.dist-info/._PKG-INFO
request_decorator_handlers-0.1.6.dist-info/._SOURCES.txt
request_decorator_handlers-0.1.6.dist-info/._dependency_links.txt
request_decorator_handlers-0.1.6.dist-info/._requires.txt
request_decorator_handlers-0.1.6.dist-info/._top_level.txt
request_decorator_handlers-0.1.6.dist-info/METADATA
request_decorator_handlers-0.1.6.dist-info/WHEEL
request_decorator_handlers-0.1.6.dist-info/top_level.txt
request_decorator_handlers-0.1.6.dist-info/RECORD
