Metadata-Version: 2.4
Name: request-decorator-handlers
Version: 0.1.6
Summary: Decorators, validators, logging and debugging helpers for async HTTP requests
Author: Evh
License-Expression: MIT
Requires-Python: >=3.10
License-File: LICENSE
Requires-Dist: jsonpath-ng>=1.7.0
Requires-Dist: loguru>=0.7.3
Requires-Dist: lxml>=4.9.0
Requires-Dist: rich>=14.2.0
Provides-Extra: dev
Requires-Dist: pytest>=8.0; extra == "dev"
Requires-Dist: pytest-asyncio>=0.23; extra == "dev"
Requires-Dist: build>=1.3.0; extra == "dev"
Requires-Dist: twine>=6.2.0; extra == "dev"
Dynamic: license-file
